[
  {
    "headword": "তিরুটি",
    "transliteration": "tiruti",
    "phonetics": "tiruṭi",
    "etymology": "[<সং ত্রুটি]",
    "senses": [
      {
        "part_of_speech": "বি.",
        "definition": "প্রমাদ; খুঁত।",
        "examples": [
          "তার কামো কুনু তিরুটি নাই।"
        ]
      }
    ],
    "source_page": "IMG_0196"
  },
  {
    "headword": "তিড়িংবিড়িং",
    "transliteration": "tido়ingbido়ing",
    "phonetics": "tiḍɔ়iŋbiḍɔ়iŋ",
    "etymology": "[<ধ্ব. তিড়িং তিড়িং ~ বিড়িং অনুকারে]",
    "senses": [
      {
        "part_of_speech": "বি.",
        "definition": "লাফালাফি; হেলাদোলা।",
        "examples": [
          "নেনায় তিড়িংবিড়িং করি আটের।",
          "সাইকেলো উঠিলে তার কমরে তিড়িংবিড়িং করে।"
        ]
      }
    ],
    "source_page": "IMG_0196"
  },
  {
    "headword": "তিলকই",
    "transliteration": "tilokoi",
    "phonetics": "tilɔkɔi",
    "etymology": "[<ববাং শব্দ তিলকই]",
    "senses": [
      {
        "part_of_speech": "বি.",
        "definition": "সরীসৃপ জাতীয় প্রাণী বিশেষ; একরকমের গোসাপ।",
        "examples": [
          "আগে বরাক উপত্যকার জঙ্গলাকীর্ণ স্থানে ঘড়িয়াল বা গোসাপের মতো আঁশহীন সরীসূপ দেখা যেত। এরা ফোঁস্ ফোঁস্ করে আওয়াজ করত। এদেরই বলা হত তিলকই। অনেকের ধারণা, এটি ছিল গোসাপের বৃহদাকার প্রজাতি বিশেষ। কারো মতে এটি প্রাগৈতিহাসিক সরীস্পের বংশধর।"
        ]
      }
    ],
    "source_page": "IMG_0196"
  },
  {
    "headword": "তিলুআ",
    "transliteration": "tilua",
    "phonetics": "tilua",
    "etymology": "[<বাং তিল + উআ তপ্র. যুক্তার্থে]",
    "senses": [
      {
        "part_of_speech": "বি.",
        "definition": "চিনি ও তিল মিশ্রিত গোলাকার মিঠাই বিশেষ।",
        "examples": [
          "বরাক উপত্যকায় পৌষপার্বনে তিলুআর ব্যবহার প্রসিদ্ধ।"
        ]
      }
    ],
    "source_page": "IMG_0196"
  },
  {
    "headword": "তিশ",
    "transliteration": "tish",
    "phonetics": "ti∫",
    "etymology": "[<ভ্রং তিস < প্রা/পা তিংস < সং ত্রিংশ]",
    "senses": [
      {
        "part_of_speech": "বিণ.",
        "definition": "৩০ সংখ্যা বা সংখ্যক।"
      }
    ],
    "source_page": "IMG_0196"
  },
  {
    "headword": "তু",
    "transliteration": "tu",
    "phonetics": "tu",
    "etymology": "[<বাং তুষ (= ধানের খোসা) সংকোচনে]",
    "senses": [
      {
        "part_of_speech": "বি.",
        "definition": "ধান প্রভৃতি শস্যের খোসা।",
        "examples": [
          "তু কুড়া আলগাইআ থ।"
        ]
      }
    ],
    "source_page": "IMG_0196"
  },
  {
    "headword": "তুয়াকুলি",
    "transliteration": "tujo়akuli",
    "phonetics": "tuʒɔ়akuli",
    "etymology": "[<আ. তুয়াককুল = ‘অনিশ্চিত’ অর্থে]",
    "senses": [
      {
        "part_of_speech": "ক্রিবিণ.",
        "definition": "ক্ষীণ আশা নিয়ে; ঈশ্বর ভরসায়।",
        "examples": [
          "হিদিন তুআকুলি গেসলাম, গিআউ কাম অই গেছে।"
        ]
      }
    ],
    "source_page": "IMG_0196"
  },
  {
    "headword": "তুইন",
    "transliteration": "tuin",
    "phonetics": "tuin",
    "etymology": "[<আমবা. তুঞি <প্রা. তুএঁ]",
    "senses": [
      {
        "part_of_speech": "সর্ব.",
        "definition": "মধ্যম পুরুষ একবচনের অসম্ভ্রমাত্মক রূপ; তুই।"
      }
    ],
    "source_page": "IMG_0196"
  },
  {
    "headword": "তুক",
    "transliteration": "tuk",
    "phonetics": "tuk",
    "etymology": "[<গুজরাটি. থুক = মুখের লালা]",
    "senses": [
      {
        "part_of_speech": "বি.",
        "definition": "থুথু।",
        "examples": [
          "জেসাখানো থুক ফালাইও না।"
        ]
      }
    ],
    "source_page": "IMG_0196"
  },
  {
    "headword": "তুকমা",
    "transliteration": "tukoma",
    "phonetics": "tukɔma",
    "etymology": "[<ফা. তুখ্ম্ = বীজ বিশেষ]",
    "senses": [
      {
        "raw_text": "[<ফা. তুখ্ম্ = বীজ বিশেষ]"
      },
      {
        "part_of_speech": "বি.",
        "definition": "তিসি জাতীয় বীজ।",
        "examples": [
          "তুকমা জলে ভেজালে সাদা ও নরম হয়। চিনি মিশিয়ে খেলে পেট শীতল হয়। ‘তুকমা চতুস্কোণ কাণ্ডযুক্ত রোমশ বর্ষজীবী বীরুৎ। পাতা সরল, বিপরীতভাবে বিন্যস্ত। ডিম্বাকৃতি, ফলকের গোড়া তাস্থুলাকার, কিনারা দম্ভর, রোমশ। নীলাভ ফুলগুলি ছোট ছোট ছত্রমঞ্জরী বা প্যানিকেল পুষ্পবিন্যাসে পাতার কক্ষে থাকে। পুষ্পপত্র আকারে ছোট। ফল গাঢ় বাদামি রঙের নাটলেট।’ — নলিনী. গাছটি পতিতজমি, টিলা ও ফসলের জমিতে বরাক উপত্যকার সর্বত্র জন্মে। বৈজ্ঞানিক নাম Hypits Suaveolens Poit."
        ]
      }
    ],
    "source_page": "IMG_0196"
  },
  {
    "headword": "তুকানি",
    "transliteration": "tukani",
    "phonetics": "tukani",
    "etymology": "[<ববাং ধাতু √ তুকা]",
    "senses": [
      {
        "part_of_speech": "ক্রি.",
        "definition": "খোঁজা; খুঁজে খুঁজে কুড়ানো।",
        "examples": [
          "তাইন কানর দুল তুকাইত্রা।",
          "আমি বরই পাড়িমু তুমি তুকাইও।"
        ]
      }
    ],
    "source_page": "IMG_0196"
  },
  {
    "headword": "তুকুমতাকুম",
    "transliteration": "tukumotakum",
    "phonetics": "tukumɔtakum",
    "etymology": "[<ববাং শব্দ তুকুম অনুকারে]",
    "senses": [
      {
        "part_of_speech": "বি.",
        "definition": "দ্বিধা।",
        "examples": [
          "হাছা মাতিতে তুইন তুকুমতাকুম করস কিতা?"
        ]
      },
      {
        "part_of_speech": "ক্রিবিণ.",
        "definition": "এদিক ওদিক।",
        "examples": [
          "তুকুমতাকুম চাস কিতা, দউড়া।"
        ]
      }
    ],
    "source_page": "IMG_0196"
  },
  {
    "headword": "তুচতাচ",
    "transliteration": "tuchotach",
    "phonetics": "tuc∫ɔtac∫",
    "etymology": "[<আঞ্চ. তুছ্ < সং তুচ্ছ]",
    "senses": [
      {
        "part_of_speech": "বি.",
        "definition": "তুচ্ছতাচ্ছিল্য।",
        "examples": [
          "তুমি আমরারে অত তুচতাচ কর কিতা?"
        ]
      }
    ],
    "source_page": "IMG_0196"
  },
  {
    "headword": "তুব",
    "transliteration": "tub",
    "phonetics": "tub",
    "etymology": "[<সং স্তৃপ = রাশি]",
    "senses": [
      {
        "part_of_speech": "বি.",
        "definition": "রাশি; স্তুপ।",
        "examples": [
          "গুপরর তুব মাটির তুব একতুব অলদি।"
        ]
      }
    ],
    "source_page": "IMG_0196"
  }
]