[
  {
    "headword": "চেরি",
    "transliteration": "cheri",
    "phonetics": "c∫eri",
    "etymology": "[< ববাং চেরা + ই লিপ্র. স্ত্রীং]",
    "senses": [
      {
        "part_of_speech": "বি.",
        "definition": "যৌবনবতী শৃকরি। ক্রিলং ত্রি erangi [< ধ্ব. ক্রিষ্ ক্রিষ্ ক্রিষ্ = বজ্রনিনাদ।",
        "cross_references": [
          "চেরা"
        ]
      },
      {
        "part_of_speech": "বি.",
        "definition": "বিদ্যুৎ সহ বজ্র নিনাদ।",
        "examples": [
          "জে চেড়েংগি দিছে হরুতায় ডরাইছইন।"
        ]
      }
    ],
    "source_page": "IMG_0147"
  },
  {
    "headword": "চেললা",
    "transliteration": "chelola",
    "phonetics": "c∫elɔla",
    "etymology": "[< বাং চেলা = কৃশাঙ্গ মাছ বিশেষ]",
    "senses": [
      {
        "part_of_speech": "বিণ.",
        "definition": "রোগা; অস্থি চর্মসার।",
        "examples": [
          "এক হাপতার কামড়িএ হে চেললা অই গেছে।"
        ]
      }
    ],
    "source_page": "IMG_0147"
  },
  {
    "headword": "চেলা",
    "transliteration": "chela",
    "phonetics": "c∫ela",
    "etymology": "[< ববাং শব্দ চেলা]",
    "senses": [
      {
        "part_of_speech": "বিণ.",
        "definition": "একপ্রকার বিষাক্ত বিছে; তেঁতুল বিছে।"
      }
    ],
    "source_page": "IMG_0147"
  },
  {
    "headword": "চেলি",
    "transliteration": "cheli",
    "phonetics": "c∫eli",
    "etymology": "[< বাং চেলা + ই তপ্র. ক্ষুদ্রার্থে]",
    "senses": [
      {
        "part_of_speech": "বি.",
        "definition": "লম্বা ফালি করা কাঠ।",
        "examples": [
          "'আজার ছেদে নাও এক ছেদে চেলি।' — বরাকপ্রবাদ >> ধ্ব. চির্চির্ = কাঠ ফাড়ার শব্দ > চিরা > চেরা ল-কারীভবনে চেলা / চেলি।"
        ]
      }
    ],
    "source_page": "IMG_0147"
  },
  {
    "headword": "চেং",
    "transliteration": "cheng",
    "phonetics": "c∫eŋ",
    "etymology": "[< আঞ্চবাং চেঙ্গ = মাছ বিশেষ]",
    "senses": [
      {
        "part_of_speech": "বি.",
        "definition": "শৌল জাতীয় ছোট মাছ বিশেষ।",
        "examples": [
          "তঃ কালরাঃ । লাকিরাঃ ঠলা এত রিবিষ্ঠাঃ । এখানঃ একে ‘জিঅলমাছ’ (ঘরের পাত্রের জলে কিছুদিন জিইয়ে রাখা যায়) বলা হয়। পোয়াতিদের পথ্য।"
        ]
      }
    ],
    "source_page": "IMG_0147"
  },
  {
    "headword": "চেংগড়বেংগড়",
    "transliteration": "chenggodo়benggodo়",
    "phonetics": "c∫eŋgɔḍɔ়beŋgɔḍɔ়",
    "etymology": "[< ধ্ব. চেংগড় = চেংমাছের লাফ অনুকারে বেংগড়।]",
    "senses": [
      {
        "part_of_speech": "বি.",
        "definition": "যন্ত্রণায় লাফালাফি।"
      }
    ],
    "source_page": "IMG_0147"
  },
  {
    "headword": "চেংগড়বেংগড় খাবা",
    "transliteration": "chenggodo়benggodo় khaba",
    "phonetics": "c∫eŋgɔḍɔ়beŋgɔḍɔ় khaba",
    "etymology": "[< দ্র. চেংগড়বেংগড়]",
    "senses": [
      {
        "part_of_speech": "সক্রি.",
        "definition": "যন্ত্রণায় গড়াগড়ি যাওয়া।",
        "examples": [
          "ভেংগুলর কামড়ে কুক্রে চেংগড়বেংগড় খার।"
        ]
      }
    ],
    "source_page": "IMG_0147"
  },
  {
    "headword": "চেংগা",
    "transliteration": "chengga",
    "phonetics": "c∫eŋga",
    "etymology": "[< ববাং শব্দ চেংগা]",
    "senses": [
      {
        "part_of_speech": "বি.",
        "definition": "মাছ রাখা ও বহন করার ঢাকনা যুক্ত টুকরি। আগে বাজারো জাউকা গি।",
        "examples": [
          "গুলবুদ্দিন আর সিরাই হরু মাছর চেংগা লইআ"
        ]
      }
    ],
    "source_page": "IMG_0147"
  },
  {
    "headword": "চেংগানি",
    "transliteration": "chenggani",
    "phonetics": "c∫eŋgani",
    "etymology": "[< বাং চাঙ্গা = সবল]",
    "senses": [
      {
        "part_of_speech": "ক্রি.",
        "definition": "সবল হওয়া; চাঙ্গা হওয়া।",
        "examples": [
          "মাছর ঝুল খাইআ খাইআ পিআরি থুড়া চেংগাইছে।"
        ]
      }
    ],
    "source_page": "IMG_0147"
  },
  {
    "headword": "চেংটা",
    "transliteration": "chengta",
    "phonetics": "c∫eŋṭa",
    "etymology": "[< ববাং শব্দ চেংটা]",
    "senses": [
      {
        "part_of_speech": "বিণ.",
        "definition": "তীব্র গন্ধযুক্ত; দুর্গন্ধযুক্ত; উগ্র।",
        "examples": [
          "কাথায়-কাপড়ে হরুতার মুতর চেংটা গন্দ।"
        ]
      }
    ],
    "source_page": "IMG_0147"
  },
  {
    "headword": "চেংড়া",
    "transliteration": "chengdo়a",
    "phonetics": "c∫eŋḍɔ়a",
    "etymology": "[< মবা. চেঙ্গড়া = চপলমতি তরুণ]",
    "senses": [
      {
        "part_of_speech": "বিণ.",
        "definition": "উঠতি বয়সি (ছেলে)।",
        "examples": [
          "চেংড়ার আবার রইদবান কিতা? >> মবা. চেঙ্গড়া দৃ. ‘ছিটাফোঁটা তন্ত্রমন্ত্র আছে কতগুলি। / চেঙ্গড়া ভুলায়ে খায় কত জানে ঠুলি।’ – অন্নদামঙ্গল"
        ]
      }
    ],
    "source_page": "IMG_0147"
  },
  {
    "headword": "চেংড়ামি",
    "transliteration": "chengdo়ami",
    "phonetics": "c∫eŋḍɔ়ami",
    "etymology": "[< ববাং চেংড়া + আমি তপ্র. ভাবার্থে]",
    "senses": [
      {
        "part_of_speech": "বি.",
        "definition": "ছ্যাবলামি; অহেতুক চঞ্চলতা।",
        "examples": [
          "অত চেংড়ামি আমার ভাললাগে না।"
        ]
      }
    ],
    "source_page": "IMG_0147"
  },
  {
    "headword": "চেংড়ি",
    "transliteration": "chengdo়i",
    "phonetics": "c∫eŋḍɔ়i",
    "etymology": "[< ববাং চেংড়া + ই লিপ্র. স্ত্রীং]",
    "senses": [
      {
        "part_of_speech": "বিণ.",
        "definition": "চেংড়ার স্ত্রী বাচক শব্দ।",
        "cross_references": [
          "চেংড়া"
        ]
      }
    ],
    "source_page": "IMG_0147"
  },
  {
    "headword": "চেংড়িফাল",
    "transliteration": "chengdo়ifal",
    "phonetics": "c∫eŋḍɔ়ifal",
    "etymology": "[< ববাং চেংগড় + ই ~ বাং লাফ]",
    "senses": [
      {
        "part_of_speech": "বি.",
        "definition": "শারীরিক যন্ত্রণায় কাতর হয়ে লাফালাফি। ছ"
      }
    ],
    "source_page": "IMG_0147"
  },
  {
    "headword": "ছআ",
    "transliteration": "chhoa",
    "phonetics": "c∫hɔa",
    "etymology": "[< বাং ছড়া = গুচ্ছ]",
    "senses": [
      {
        "part_of_speech": "বি.",
        "definition": "গুচ্ছ. কাঁদি।",
        "examples": [
          "একছআ গুআ; দুই ছআ ভূবি; ছআ ছআ ধান।"
        ]
      }
    ],
    "source_page": "IMG_0147"
  },
  {
    "headword": "ছআৢ",
    "transliteration": "chhoaৢ",
    "phonetics": "c∫hɔaৢ",
    "etymology": "[< মবা. ছোআ = ছোঁয়া]",
    "senses": [
      {
        "part_of_speech": "ক্রি.",
        "definition": "স্পর্শ করা।",
        "examples": [
          "পরশ তনে আইআ মোরে ছইস না।"
        ]
      }
    ],
    "source_page": "IMG_0147"
  },
  {
    "headword": "ছআছুতি",
    "transliteration": "chhoachhuti",
    "phonetics": "c∫hɔac∫huti",
    "etymology": "[< আঞ্চবাং ছুঁআছুই]",
    "senses": [
      {
        "part_of_speech": "বি.",
        "definition": "যা স্পর্শ করা উচিত নয় তা স্পর্শ করে ফেলার ব্যাপার।",
        "examples": [
          "ছআছুতিএ দাউদ চউকউঠা ইতা হাসরে।"
        ]
      }
    ],
    "source_page": "IMG_0147"
  },
  {
    "headword": "ছই",
    "transliteration": "chhoi",
    "phonetics": "c∫hɔi",
    "etymology": "[< সং ছিষ]",
    "senses": [
      {
        "part_of_speech": "বি.",
        "definition": "নৌকা বা গোরুর গাড়ির চাল।",
        "examples": [
          "গুনটি নাওত ছই থাকে। লা ভাষার অভিধান ও ভাষাতত্ত"
        ]
      },
      {
        "part_of_speech": "বি.",
        "definition": "পিঠে দেওয়ার ছাতা; Back Umbrella.",
        "examples": [
          "রোদ-বৃষ্টি থেকে পিঠ বাঁচানোর জন্য কৃষকদের ব্যবহৃত ডিম্বাকার ছাতা বিশেষ। বেত ও ছাতিম পাতা দিয়ে তৈরি।"
        ]
      }
    ],
    "source_page": "IMG_0147"
  }
]