[
  {
    "headword": "ফেটিআ",
    "transliteration": "fetia",
    "phonetics": "feṭia",
    "etymology": "[< ববাং শব্দ ফেটিআ]",
    "senses": [
      {
        "part_of_speech": "বি.",
        "definition": "কই জাতীয় রঙিন ছোট মাছ।",
        "examples": [
          "বাহারে পাঁতি বিন্যাস এই ছোটমাছকে বিশিষ্ট করে তুলেছে। নতুন বৃষ্টিতে কই মাছের সঙ্গে উজিয়ে থাকে। খেতে খুবই ভালো।"
        ]
      },
      {
        "part_of_speech": "বাগধা. ক্রি.",
        "definition": "অতি আদুরে হওয়ার দরুণ সামান্য শ্রমে ভেঙে পড়া।",
        "examples": [
          "জেতা বেটিনতর ফেত করতে নথ পড়ি জায় ইতারে আনিআ মোর ঘর চলত নায়। কাং তুল. ‘ফুলের ঘায়ে মূর্ছা যাওয়া।’"
        ]
      }
    ],
    "source_page": "IMG_0251"
  },
  {
    "headword": "ফেত্রা",
    "transliteration": "fetra",
    "phonetics": "fetra",
    "etymology": "[< ববাং পাত (<পাতা) + রা বহুবচনে]",
    "senses": [
      {
        "part_of_speech": "বিণ.",
        "definition": "কলাপাতার মতো ছিঁড়ে ফালি ফালি হয়ে গেছে এমন।",
        "examples": [
          "গাইনছাখান এখেরে ফেত্রা অইগেছে আর পিনধা জাইত নায়।"
        ]
      }
    ],
    "source_page": "IMG_0251"
  },
  {
    "headword": "ফেতেড়া",
    "transliteration": "fetedo়a",
    "phonetics": "feteḍɔ়a",
    "etymology": "[< ববাং শব্দ ফেতেড়া]",
    "senses": [
      {
        "part_of_speech": "বিণ.",
        "definition": "কাহিল; জীর্ণ।",
        "examples": [
          "মাটিকামে শরীল ফেতেড়া বানাইলায়।"
        ]
      },
      {
        "part_of_speech": "বিণ.",
        "definition": "সহজে ক্লান্ত হয় না এমন; নাছোড়বান্দা।",
        "examples": [
          "বাংগাল কামো বড় ফেতেড়া।"
        ]
      }
    ],
    "source_page": "IMG_0251"
  },
  {
    "headword": "ফেদা",
    "transliteration": "feda",
    "phonetics": "feda",
    "etymology": "[< আঞ্চ. ফ্যাদা = লিঙ্গের ক্লেদ]",
    "senses": [
      {
        "part_of_speech": "বি.",
        "definition": "ময়লা; গায়ের মল।",
        "examples": [
          "ফেদা লাগিআ আংগরখা ছাকা ছাকা অই রইছে।"
        ]
      }
    ],
    "source_page": "IMG_0251"
  },
  {
    "headword": "ফেনকচু",
    "transliteration": "fenokochu",
    "phonetics": "fenɔkɔc∫u",
    "etymology": "[< ফেন (< সং ফণা) ~ কচু]",
    "senses": [
      {
        "part_of_speech": "বি.",
        "definition": "উৎকৃষ্ট মানকচু।",
        "examples": [
          "বড়জাতের এই কচুর পাতা বিশাল ও সবুজ মসৃণ। কন্দ মোটা দীর্ঘ হয়। ভেতরটা দুধসাদা। ভেষজ, খাদ্যগুণ ও উপকারিতায় সবার সেরা। নানা রোগের জন্য এর লোকায়ত ব্যবহার প্রসিদ্ধ।"
        ]
      }
    ],
    "source_page": "IMG_0251"
  },
  {
    "headword": "ফেনা",
    "transliteration": "fena",
    "phonetics": "fena",
    "etymology": "[< ববাং শব্দ ফেনা]",
    "senses": [
      {
        "part_of_speech": "বি.",
        "definition": "কৌটো, বয়াম বা বোতলের ছিপি।",
        "examples": [
          "দুদর ডিবির ফেনা কানো ফালাইছত্।"
        ]
      }
    ],
    "source_page": "IMG_0251"
  },
  {
    "headword": "ফেনি",
    "transliteration": "feni",
    "phonetics": "feni",
    "etymology": "[< ববাং শব্দ ফেনি]",
    "senses": [
      {
        "raw_text": "[< ববাং শব্দ ফেনি]"
      },
      {
        "part_of_speech": "বি.",
        "definition": "বাঁশের খুঁটিকে অবলম্বন করে গড়ে তোলা গম্বুজাকৃতি খড়ের গাদা; পালুই।",
        "examples": [
          "বনদো এক চিমটি ঘা নাই দামাগুরে ফেনিত লাগাইআ থ।"
        ]
      }
    ],
    "source_page": "IMG_0251"
  },
  {
    "headword": "ফেপড়া",
    "transliteration": "fepodo়a",
    "phonetics": "fepɔḍɔ়a",
    "etymology": "[< ববাং শব্দ ফেপড়া]",
    "senses": [
      {
        "part_of_speech": "বিণ.",
        "definition": "সহজে চেরা বা ফাড়া যায় না এমন; দুশ্ছেদা।",
        "examples": [
          "তেতই গাছ বড় ফেপড়া।"
        ]
      },
      {
        "part_of_speech": "বিণ.",
        "definition": "আয়ত্তে আনা সহজ নয় এমন।"
      }
    ],
    "source_page": "IMG_0251"
  },
  {
    "headword": "ফেপড়ি",
    "transliteration": "fepodo়i",
    "phonetics": "fepɔḍɔ়i",
    "etymology": "[< ধ্ব ফড়ফড় ক্রোধসূচক]",
    "senses": [
      {
        "part_of_speech": "বি.",
        "definition": "রাগ মেশানো হুমকি; তাড়া; আক্রমণের উদ্যোগ।"
      }
    ],
    "source_page": "IMG_0251"
  },
  {
    "headword": "ফের",
    "transliteration": "fer",
    "phonetics": "fer",
    "etymology": "[< মবা. ফের = গণ্ডগোল]",
    "senses": [
      {
        "part_of_speech": "বি.",
        "definition": "পাল্লার ওজনের তারতম্য; দাঁড়িপাল্লা বা তৌলযন্ত্রের ভারসাম্যের অনুপস্থিতি।",
        "examples": [
          "পাল্লার ফের ভাংগিআ মাপো বা।"
        ]
      },
      {
        "part_of_speech": "বাগধা. ক্রি.",
        "definition": "ওজন করার আগে দাঁড়িপাল্লার সমতা ঠিক করা।",
        "examples": [
          "আগে পাল্লার ফের ভাংগো বাদে মাল মাপো।"
        ]
      }
    ],
    "source_page": "IMG_0251"
  },
  {
    "headword": "ফেরত",
    "transliteration": "ferot",
    "phonetics": "ferɔt",
    "etymology": "[< দ্র. পেরত]",
    "senses": [
      {
        "part_of_speech": "বিণ.",
        "definition": "অপরিচ্ছন্ন হয়ে থাকে এমন; নোংরা।",
        "examples": [
          "বেটাগু বড় ফেরত, জেনো-অনো কাশ-ছেপ ফালায়।"
        ]
      }
    ],
    "source_page": "IMG_0251"
  },
  {
    "headword": "ফেরতি",
    "transliteration": "feroti",
    "phonetics": "ferɔti",
    "etymology": "[< ববাং ফেরত +ই লিপ্র স্ত্রীং]",
    "senses": [
      {
        "part_of_speech": "বিণ.",
        "definition": "‘ফেরত’ এর স্ত্রীবাচক শব্দ।"
      }
    ],
    "source_page": "IMG_0251"
  },
  {
    "headword": "ফেরতামি",
    "transliteration": "ferotami",
    "phonetics": "ferɔtami",
    "etymology": "[< ববাং ফেরত + আমি তপ্র ভাবার্থো]",
    "senses": [
      {
        "part_of_speech": "বি.",
        "definition": "ফেরতের আচরণ; নোংরামি। ফেরফেরা — ferfera [< ধ্ব. ফের্ফের্ = পাতলা বুনন; ছিঁড়ে যাওয়ার উপক্রম; জীর্ণতাসূচক।"
      },
      {
        "part_of_speech": "বিণ.",
        "definition": "ঠাস বুনন নয় এমন; জীর্ণ।",
        "examples": [
          "ই হাড়িখান একেরে ফেরফেরা।"
        ]
      }
    ],
    "source_page": "IMG_0251"
  },
  {
    "headword": "ফৈরা",
    "transliteration": "foira",
    "phonetics": "fɔĭra",
    "etymology": "[< ববাং শব্দ ফেরা]",
    "senses": [
      {
        "part_of_speech": "বি.",
        "definition": "ঘামাচির মতো একপ্রকার প্রদাহযুক্ত গুটিকা নির্গমনকারী সংক্রামক জুর বিশেষ; হাম; Measles লাল রঙের পীড়কা উঠে।’ — ড. যোগেশ চন্দ্র ঘোষ। ",
        "examples": [
          "‘প্রথমে সর্দির লক্ষণ প্রকাশ প্রায়; হাঁচি হয় ও নাক দিয়া জল পড়ে; চক্ষু লাল হয় ও ছলছল করে: কপাল পিঠ ও শরীরে বেদনা অনুভূত হয়; কাশি হয় গলা ভাঙিয়া যায় এবং জুর হয়। চতুর্থ দিনে প্রথমত মুখে ও গলায় এবং, পরে সমস্ত শরীরে ছোট লা ভাষার <mark>অ</mark>ভিধান ও ভাষাতত্ত্ব"
        ]
      }
    ],
    "source_page": "IMG_0251"
  }
]