[
  {
    "headword": "বুদ্রা",
    "transliteration": "budra",
    "phonetics": "budra",
    "etymology": "[< ববাং শব্দ বুদরা]",
    "senses": [
      {
        "part_of_speech": "বিণ.",
        "definition": "পানসে স্বাদযুক্ত।",
        "examples": [
          "বুদরা কাঠল কিগে আনছে?"
        ]
      },
      {
        "part_of_speech": "বিণ.",
        "definition": "ফ্যাকাশে [রং বিষয়ে]।",
        "examples": [
          "বুদরা রংগর হাড়ি মোর লগে আনিও না। বুদ"
        ]
      },
      {
        "part_of_speech": "বিণ.",
        "definition": "ভণ্ড ও শয়তান।",
        "examples": [
          "হে ভেকে বইরাগি আসলে বুদহিআল।"
        ]
      }
    ],
    "source_page": "IMG_0277"
  },
  {
    "headword": "বুদাই",
    "transliteration": "budai",
    "phonetics": "budai",
    "etymology": "[< আঞ্চ. বুতা + ই তপ্র. আদরে]",
    "senses": [
      {
        "part_of_speech": "বি.",
        "definition": "আহাম্মক।",
        "examples": [
          "অলা বুদাই অইলে এলকুর দুনিআত খাবা জায় না।"
        ]
      }
    ],
    "source_page": "IMG_0277"
  },
  {
    "headword": "বুধ",
    "transliteration": "budh",
    "phonetics": "budh",
    "etymology": "[< সং √বুধ]",
    "senses": [
      {
        "part_of_speech": "বি.",
        "definition": "উপলব্ধি; টের।"
      }
    ],
    "source_page": "IMG_0277"
  },
  {
    "headword": "বুধ পাবা",
    "transliteration": "budh paba",
    "phonetics": "budh paba",
    "etymology": "[< বরাং বুধ ~ √পা]",
    "senses": [
      {
        "part_of_speech": "সক্রি.",
        "definition": "বুঝতে পারা; টের পাওয়া।",
        "examples": [
          "সংসার চালাইলে না বুধ পাইতে ক ধানে কয় চাউল।"
        ]
      }
    ],
    "source_page": "IMG_0277"
  },
  {
    "headword": "বুনদা",
    "transliteration": "bunoda",
    "phonetics": "bunɔda",
    "etymology": "[< ববাং শব্দ বুনদা]",
    "senses": [
      {
        "part_of_speech": "বি.",
        "definition": "আটি; bundle।",
        "examples": [
          "পুননা কাগচ্টাইন বুনদা বলি থ।"
        ]
      },
      {
        "part_of_speech": "বি.",
        "definition": "ঘরের কোণার বেড়া।",
        "examples": [
          "ইআন কুনার বুনদা কাটিআ চুর হুমাইগেশলা।"
        ]
      }
    ],
    "source_page": "IMG_0277"
  },
  {
    "headword": "বুনি",
    "transliteration": "buni",
    "phonetics": "buni",
    "etymology": "[< আবুক = স্তন]",
    "senses": [
      {
        "part_of_speech": "বি.",
        "definition": "দুধে ভরা স্তন; সস্তানবতীর স্তন।",
        "examples": [
          "কুমারীর স্তনকে বলা হয় ‘বুচি’। দ্র. বুচি",
          "কাইল তনে মোর বুনির দুদ হুকাই গেছে।"
        ]
      }
    ],
    "source_page": "IMG_0277"
  },
  {
    "headword": "বুনি আগা",
    "transliteration": "buni aga",
    "phonetics": "buni aga",
    "etymology": "[< ববাং বুনি + আগা (=৩)]",
    "senses": [
      {
        "part_of_speech": "বি.",
        "definition": "কোলের শিশুর উদরাময়।",
        "examples": [
          "হরুতার বুনিআগা অইলে চিনি লবনর পানি খাবাইন।"
        ]
      }
    ],
    "source_page": "IMG_0277"
  },
  {
    "headword": "বুম বাদাল",
    "transliteration": "bum badal",
    "phonetics": "bum badal",
    "etymology": "[< ববাং শব্দ বুম ~ বাদাল]",
    "senses": [
      {
        "part_of_speech": "বি.",
        "definition": "শালি ধান বিশেষ।",
        "examples": [
          "শালি ধানের অন্তর্গত আসরা ধানের প্রকার বিশেষ। বড় দানার ধান। সাদা রং। চালও সাদা।"
        ]
      }
    ],
    "source_page": "IMG_0277"
  },
  {
    "headword": "বুরগা",
    "transliteration": "buroga",
    "phonetics": "burɔga",
    "etymology": "[< বাং বোরখা ঘোষীভবনে < আ. বুর্ক]",
    "senses": [
      {
        "part_of_speech": "বি.",
        "definition": "আপাদমস্তক ঢাকা মুসলমান নারীদের গাত্রাবরণ।",
        "examples": [
          "বুরগা পিন্দ্রা বেটিন এলকু বেশ চউখো পড়ে ন।"
        ]
      }
    ],
    "source_page": "IMG_0277"
  },
  {
    "headword": "বুরবুর",
    "transliteration": "burobur",
    "phonetics": "burɔbur",
    "etymology": "[< ধ্ব. বুরবুর]",
    "senses": [
      {
        "raw_text": "[< ধ্ব. বুরবুর]"
      }
    ],
    "source_page": "IMG_0277"
  },
  {
    "headword": "_continuation",
    "transliteration": "",
    "phonetics": "",
    "senses": [
      {
        "raw_text": "২১৭ বুড়াকি ধ্ব. — ফুটো দিয়ে জল ঢোকার আওয়াজ।"
      }
    ],
    "source_page": "IMG_0277"
  },
  {
    "headword": "বুরা",
    "transliteration": "bura",
    "phonetics": "bura",
    "etymology": "[< আঞ্চ. হি. বুরা]",
    "senses": [
      {
        "part_of_speech": "বিণ.",
        "definition": "মন্দ।",
        "examples": [
          "ভালা বুরা মানু বুঝিআ চলিঅ।"
        ]
      }
    ],
    "source_page": "IMG_0277"
  },
  {
    "headword": "বুরি",
    "transliteration": "buri",
    "phonetics": "buri",
    "etymology": "[< আমবা. ভুরুহী < সং ভু]",
    "senses": [
      {
        "part_of_speech": "বি.",
        "definition": "চোখের উপরে কপালের অধোভাগে সুদৃশ্য রোমাবলি। >> আমবা. ভুরুহী দৃ. ‘কাল ভুরুহী শোভে বদন কমলে।’ —কৃকী। অল্পপ্রাণিত ও সংকোচনে বরাক বাংলায় ‘বুরি’।"
      }
    ],
    "source_page": "IMG_0277"
  },
  {
    "headword": "বুরি",
    "transliteration": "buri",
    "phonetics": "buri",
    "etymology": "[< ধ্ব. বুরবুর = বুদবুদ ওঠার শব্দ]",
    "senses": [
      {
        "part_of_speech": "বি.",
        "definition": "বুদবুদ।",
        "examples": [
          "চিতল মাছে বুরি তুলের।"
        ]
      }
    ],
    "source_page": "IMG_0277"
  },
  {
    "headword": "বুরুত্তি",
    "transliteration": "burutti",
    "phonetics": "burutti",
    "etymology": "[< ধ্ব. বুরুৎ আকস্মিকতা বাচক]",
    "senses": [
      {
        "part_of_speech": "ক্রিবিণ.",
        "definition": "হঠাৎ; ফুডুৎ করে।",
        "examples": [
          "বাদাত আত দিতেউ পাক্খি বুরুত্তি উড়াল দি গেছে গি।"
        ]
      }
    ],
    "source_page": "IMG_0277"
  },
  {
    "headword": "বুবাই",
    "transliteration": "bubai",
    "phonetics": "bubai",
    "etymology": "[< বুবু (=বোন) + আই সাদৃশ্যে]",
    "senses": [
      {
        "part_of_speech": "বি.",
        "definition": "দিদি; বউদিদি।",
        "examples": [
          "শব্দটি কেবল মুসলমান সমাজেই প্রচলিত।"
        ]
      }
    ],
    "source_page": "IMG_0277"
  },
  {
    "headword": "বুড়",
    "transliteration": "budo়",
    "phonetics": "buḍɔ়",
    "etymology": "[< দ্র. বুড়া]",
    "senses": [
      {
        "part_of_speech": "বি.",
        "definition": "ডুব।",
        "examples": [
          "মুই এক বুড়ে গাং পারইতাম, দেখতে?"
        ]
      },
      {
        "part_of_speech": "বাগধা. ক্রি.",
        "definition": "স্নান করা।",
        "examples": [
          "গরমর দিন মুই বিআন বিআল বুড় পাড়ি।"
        ]
      }
    ],
    "source_page": "IMG_0277"
  },
  {
    "headword": "বুড়বখ",
    "transliteration": "budo়bokh",
    "phonetics": "buḍɔ়bɔkh",
    "etymology": "[< হি. বুঢ়াবক্ক = কাণ্ডজ্ঞানহীন]",
    "senses": [
      {
        "part_of_speech": "বিণ.",
        "definition": "বোকা; স্থূলবুদ্ধি সম্পন্ন।",
        "examples": [
          "বুড়বখ মানু দি মোর বেপার চলত নায়।"
        ]
      }
    ],
    "source_page": "IMG_0277"
  },
  {
    "headword": "বুড়া",
    "transliteration": "budo়a",
    "phonetics": "buḍɔ়a",
    "etymology": "[< আঞ্চবাং. বুড় (আ) < সং ব্রুড্ Ì নিমজ্জনে]",
    "senses": [
      {
        "part_of_speech": "ক্রি.",
        "definition": "জলে ডোবা।",
        "examples": [
          "হাতার না-জানলে লামিস না, বুড়িবে।"
        ]
      },
      {
        "part_of_speech": "ক্রি.",
        "definition": "তরল পদার্থে ডোবা; কাদা বা তেলে মাখামাখি হওয়া।",
        "examples": [
          "তাই অলা তেল মাখিছে, দেখা জার তেলো বুড়িআ আইসে।"
        ]
      }
    ],
    "source_page": "IMG_0277"
  },
  {
    "headword": "বুড়ানি",
    "transliteration": "budo়ani",
    "phonetics": "buḍɔ়ani",
    "etymology": "[< ববাং √বুড় + আ(নি) ণিজন্তে]",
    "senses": [
      {
        "part_of_speech": "ক্রি.",
        "definition": "তরল পদার্থে ডোবানো।",
        "examples": [
          "চরাগু দুদো বুড়াইআ থ।"
        ]
      }
    ],
    "source_page": "IMG_0277"
  },
  {
    "headword": "বুড়াকি",
    "transliteration": "budo়aki",
    "phonetics": "buḍɔ়aki",
    "etymology": "[< বাং বুড়া + কি তপ্র. ভাবার্থে]",
    "senses": [
      {
        "part_of_speech": "বি.",
        "definition": "বৃদ্ধদশা; বুড়োপনা।"
      }
    ],
    "source_page": "IMG_0277"
  }
]