[
  {
    "headword": "_continuation",
    "transliteration": "",
    "phonetics": "",
    "senses": [
      {
        "part_of_speech": "ক্রি.",
        "definition": "শেখা; অনুশীলন করা; শিক্ষা গ্রহণ করা; f অধ্যয়ন করা।",
        "examples": [
          "ভালা পড়ডাহকলে রুজর পড়া রুজ হিখইন।",
          "কার গেছে অংক (=অঙ্ক) হিখস।"
        ]
      }
    ],
    "source_page": "IMG_0346"
  },
  {
    "headword": "হিখানি",
    "transliteration": "hikhani",
    "phonetics": "ɦikhani",
    "etymology": "[< বাং শিখা হকারীভবনে ণিজস্তে]",
    "senses": [
      {
        "part_of_speech": "ক্রি.",
        "definition": "শেখানো; শিক্ষা দেওয়া।",
        "examples": [
          "ছয়ফুল মিআর গেছে গেলে তাইন কবিগান হিখাইবা।"
        ]
      },
      {
        "part_of_speech": "ক্রি.",
        "definition": "আলং — প্রতিশোধ লওয়া।",
        "examples": [
          "হে আমারে জেতা করছে একদিন তারে হিখাইমূ f ক-ধানে ক-চাউল।"
        ]
      }
    ],
    "source_page": "IMG_0346"
  },
  {
    "headword": "হিগু",
    "transliteration": "higu",
    "phonetics": "ɦigu",
    "etymology": "[< ববাং উপ্র. হি + আমবা. গুটি (= টি, টা) সংকোচনে]",
    "senses": [
      {
        "part_of_speech": "সর্ব.",
        "definition": "সে [অসন্ত্রমার্থে]।",
        "examples": [
          "অতবিল তনে হিগু কানো গেছে?"
        ]
      },
      {
        "part_of_speech": "সর্ব.",
        "definition": "ওইটা; অন্যটি [দূরনির্দেশক]।",
        "examples": [
          "তুইন তো এগ্গু পাইসত্, হিগু মোরে দিস। >> আমবা. দৃ. ‘বাঁশীগুটি থুইহ তোন্ধে কলসি ভীতর।’ — কৃকী হিণ্<mark>ডইন</mark> fiiguin [< ববাং উপ্র. হি + আমবা. গুটি + ইন বহুত্ববোধক প্রত্যয়]"
        ]
      },
      {
        "part_of_speech": "সর্ব.",
        "definition": "ওরা [অসন্ত্রমার্থে]।",
        "examples": [
          "হিগুইন কুনবায় নিভিছইন বিচরাইআ পাইআর না।"
        ],
        "cross_references": [
          "গুইন"
        ]
      },
      {
        "part_of_speech": "সর্ব.",
        "definition": "ওইগুলো; অন্যগুলি।",
        "examples": [
          "ইগুইন কিবার মোরে দিলায় হিগুইন কারে দিতায় ?",
          "ইগুইনতে হিগুইনতে কিতা বেশকম (= পার্থক্য)?"
        ]
      }
    ],
    "source_page": "IMG_0346"
  },
  {
    "headword": "হিচা",
    "transliteration": "hicha",
    "phonetics": "ɦic∫a",
    "etymology": "[< সং সিচ্ (=সেচন করা) হকারীভবনে]",
    "senses": [
      {
        "part_of_speech": "ক্রি.",
        "definition": "সেচন করা।",
        "examples": [
          "ডাংগার গুটিত ডম্কাদি পানি হিচিমু।"
        ]
      }
    ],
    "source_page": "IMG_0346"
  },
  {
    "headword": "হিজা",
    "transliteration": "hija",
    "phonetics": "ɦiʒa",
    "etymology": "[< বাং শীষ < সং শীর্ষ]",
    "senses": [
      {
        "part_of_speech": "বি.",
        "definition": "ধানের ছড়া; ধানের শিষ; ধানের মঞ্জরি।",
        "examples": [
          "হাইল ধানে হিজা ছাড়ের।"
        ]
      }
    ],
    "source_page": "IMG_0346"
  },
  {
    "headword": "হিজা্ব",
    "transliteration": "hijabo",
    "phonetics": "ɦiʒabɔ",
    "etymology": "[< প্রা. সিধ. < সং সিদ্ধ]",
    "senses": [
      {
        "part_of_speech": "ক্রি.",
        "definition": "সেদ্ধ হওয়া; নরম হওয়া।",
        "examples": [
          "‘শাইর কাটি সরলা ঝিংগা রানধে হিজে না।’ — বরাক ছড়া"
        ]
      }
    ],
    "source_page": "IMG_0346"
  },
  {
    "headword": "_continuation",
    "transliteration": "",
    "phonetics": "",
    "senses": [
      {
        "raw_text": "বরাক বাংলায় হিঝ্ বা হিজ্। দ্র. মজা।"
      }
    ],
    "source_page": "IMG_0346"
  },
  {
    "headword": "হিটা",
    "transliteration": "hita",
    "phonetics": "ɦiṭa",
    "etymology": "[< ববাং শব্দ হিটা]",
    "senses": [
      {
        "part_of_speech": "বিণ.",
        "definition": "বাসি: টাটকা নয়; আগের দিনে প্রস্তুত এমন",
        "examples": [
          "হিটা বেনজন মুই খাইতু না।"
        ]
      }
    ],
    "source_page": "IMG_0346"
  },
  {
    "headword": "হিটি",
    "transliteration": "hiti",
    "phonetics": "ɦiṭi",
    "etymology": "[< ববাং হিটা + ই তপ্র. ভাবার্থে]",
    "senses": [
      {
        "part_of_speech": "বি.",
        "definition": "পোড়া তামাক; গুল।",
        "examples": [
          "হিটি দি দাত মানজিলে দাত ভালা রয়।"
        ]
      },
      {
        "part_of_speech": "বি.",
        "definition": "দাঁত বা শরীরের ময়লা।",
        "examples": [
          "হিটি লাগাইল দাঁত লইআ ইশকুলো আইস না।"
        ]
      }
    ],
    "source_page": "IMG_0346"
  },
  {
    "headword": "হিটিমিটি",
    "transliteration": "hitimiti",
    "phonetics": "ɦiṭimiṭi",
    "etymology": "[< ববাং হিটি অনুকারে ~ মিটি]",
    "senses": [
      {
        "part_of_speech": "বিণ.",
        "definition": "ছোটখাটো; কম পুঁজির।",
        "examples": [
          "সবিএ পথর ধারো হিটিমিটি একখান চা’র অটল ফিত্ম।"
        ]
      },
      {
        "part_of_speech": "বাগধা. ক্রি.",
        "definition": "অহেতুক দাঁত বের করে হাসা।",
        "examples": [
          "কুনতা বুধ পাস নি, খালি হিটিহিটি করস।"
        ]
      },
      {
        "part_of_speech": "বাগধা. ক্রি.",
        "definition": "দাঁত বের করে হাসা। ⇔ ক্রিয়াটি ব্যঙ্গার্থে ব্যবহৃত হয়।"
      }
    ],
    "source_page": "IMG_0346"
  },
  {
    "headword": "হিতা",
    "transliteration": "hita",
    "phonetics": "ɦita",
    "etymology": "[< ববাং উপ্র. হি + তা (< বাং তাহা) বহুত্ববোধক প্রত্যয় ]",
    "senses": [
      {
        "raw_text": "[< ববাং উপ্র. হি + তা (< বাং তাহা) বহুত্ববোধক প্রত্যয় ] সধ. — ওইগুলি ; ওরা [অসম্ভ্রমাত্মক্ ⇒ হিতা পানিত রইতে রইতে পচের। ⇒ জেতা রইছে হিতা কিগে খাইত। ⇒ হিতা আইছইন না নি আবো? ≫ বরাক বাংলায় প্রথম পুরুষের বহুবচনে উপসর্গীয় প্রত্যয় হি + তা > হিতা বহুত্ববোধক প্রত্যয়ে গঠিত হয়েছে তির্যক কারকে সর্বনাম পদ।"
      }
    ],
    "source_page": "IMG_0346"
  },
  {
    "headword": "হিথান",
    "transliteration": "hithan",
    "phonetics": "ɦithan",
    "etymology": "[< বাং শিথান হকারী ভবনে < সং শিরঃ স্থান ]",
    "senses": [
      {
        "part_of_speech": "বি.",
        "definition": "শায়িত ব্যক্তির মাথর দিক; শিয়র।",
        "examples": [
          "হিথানো বালিশ দিআ ঘুমা।"
        ]
      }
    ],
    "source_page": "IMG_0346"
  },
  {
    "headword": "হিদল",
    "transliteration": "hidol",
    "phonetics": "ɦidɔl",
    "etymology": "[< আঞ্চবাং শিদল হকারীভবনে]",
    "senses": [
      {
        "part_of_speech": "বি.",
        "definition": "বিশেষ পদ্ধতিতে পচানো শুকনো মাছ।",
        "examples": [
          "পুঁটি, তেলেশ প্রভৃতি মাছ শুকিয়ে বিশেষ পদ্ধতিতে পচিয়ে হিদল তৈরি করা হয়। ত্রিপুরা; বরাক উপত্যকা ও পূর্ববঙ্গের বাঙালি ছাড়াও উত্তর পূর্বাঞ্চলের কুকি ডিমাসা মণিপুরি রিয়াং চাকমা প্রভৃতি উপজাতিদের অতি প্রিয় খাদ্য।",
          "'গরিবর গরিবানা/ হিদল দি চালিপিঠা খানা।' বরাকপ্রবাদ"
        ]
      }
    ],
    "source_page": "IMG_0346"
  }
]